tests/__init__.py
tests/message_test.py
tests/subscriber_test.py
tests/topic_test.py
topiq/__init__.py
topiq/_topic_event.py
topiq/_topic_reader.py
topiq/_topic_utils.py
topiq/_topic_writer.py
topiq/consumer.py
topiq/message.py
topiq/message_type.py
topiq/partition.py
topiq/subscriber.py
topiq/topic.py
topiq/topic_error.py
topiq/version.py
topiq-0.1.1b1.dist-info/LICENSE
topiq-0.1.1b1.dist-info/METADATA
topiq-0.1.1b1.dist-info/WHEEL
topiq-0.1.1b1.dist-info/top_level.txt
topiq-0.1.1b1.dist-info/RECORD
